{
  "updated_iso": "2026-04-28T07:18:00+00:00",
  "latest": {
    "epoch": 172000000,
    "H": 2.277,
    "unique": 557,
    "ops": 103.108,
    "reps": 105,
    "cat": 0.2059,
    "raf": 1216.843,
    "cyc": 7,
    "rate": 5097.0,
    "edges": 2779
  },
  "history": [
    {
      "epoch": 113000000,
      "H": 2.127,
      "unique": 517,
      "ops": 103.457,
      "reps": 105,
      "cat": 0.202,
      "raf": 1194.016,
      "cyc": 4,
      "rate": 5293.0,
      "edges": 2795
    },
    {
      "epoch": 114000000,
      "H": 2.32,
      "unique": 562,
      "ops": 102.196,
      "reps": 106,
      "cat": 0.2166,
      "raf": 1280.08,
      "cyc": 3,
      "rate": 5273.0,
      "edges": 2767
    },
    {
      "epoch": 115000000,
      "H": 1.996,
      "unique": 500,
      "ops": 103.585,
      "reps": 87,
      "cat": 0.2006,
      "raf": 1185.517,
      "cyc": 10,
      "rate": 5255.0,
      "edges": 2780
    },
    {
      "epoch": 116000000,
      "H": 2.223,
      "unique": 549,
      "ops": 102.982,
      "reps": 106,
      "cat": 0.2073,
      "raf": 1225.514,
      "cyc": 4,
      "rate": 5236.0,
      "edges": 2780
    },
    {
      "epoch": 117000000,
      "H": 2.199,
      "unique": 538,
      "ops": 102.523,
      "reps": 107,
      "cat": 0.2125,
      "raf": 1256.053,
      "cyc": 6,
      "rate": 5222.0,
      "edges": 2780
    },
    {
      "epoch": 118000000,
      "H": 2.143,
      "unique": 510,
      "ops": 103.179,
      "reps": 107,
      "cat": 0.205,
      "raf": 1211.547,
      "cyc": 7,
      "rate": 5211.0,
      "edges": 2827
    },
    {
      "epoch": 119000000,
      "H": 2.33,
      "unique": 548,
      "ops": 102.123,
      "reps": 118,
      "cat": 0.2174,
      "raf": 1284.714,
      "cyc": 3,
      "rate": 5199.0,
      "edges": 2708
    },
    {
      "epoch": 120000000,
      "H": 2.577,
      "unique": 592,
      "ops": 100.651,
      "reps": 136,
      "cat": 0.2344,
      "raf": 1385.405,
      "cyc": 15,
      "rate": 5177.0,
      "edges": 2641
    },
    {
      "epoch": 121000000,
      "H": 2.05,
      "unique": 493,
      "ops": 102.663,
      "reps": 88,
      "cat": 0.2108,
      "raf": 1245.982,
      "cyc": 3,
      "rate": 5148.0,
      "edges": 2650
    },
    {
      "epoch": 122000000,
      "H": 1.764,
      "unique": 447,
      "ops": 105.273,
      "reps": 78,
      "cat": 0.1809,
      "raf": 1069.499,
      "cyc": 10,
      "rate": 5112.0,
      "edges": 2678
    },
    {
      "epoch": 123000000,
      "H": 1.58,
      "unique": 386,
      "ops": 107.512,
      "reps": 68,
      "cat": 0.1554,
      "raf": 918.509,
      "cyc": 8,
      "rate": 5073.0,
      "edges": 2702
    },
    {
      "epoch": 124000000,
      "H": 1.638,
      "unique": 426,
      "ops": 107.132,
      "reps": 58,
      "cat": 0.1597,
      "raf": 944.178,
      "cyc": 1,
      "rate": 5042.0,
      "edges": 2726
    },
    {
      "epoch": 125000000,
      "H": 1.987,
      "unique": 479,
      "ops": 105.451,
      "reps": 101,
      "cat": 0.1791,
      "raf": 1058.854,
      "cyc": 3,
      "rate": 5011.0,
      "edges": 2708
    },
    {
      "epoch": 126000000,
      "H": 1.975,
      "unique": 495,
      "ops": 104.488,
      "reps": 84,
      "cat": 0.19,
      "raf": 1122.8,
      "cyc": 9,
      "rate": 4973.0,
      "edges": 2700
    },
    {
      "epoch": 127000000,
      "H": 1.722,
      "unique": 420,
      "ops": 106.129,
      "reps": 84,
      "cat": 0.1713,
      "raf": 1012.51,
      "cyc": 12,
      "rate": 4933.0,
      "edges": 2698
    },
    {
      "epoch": 128000000,
      "H": 1.48,
      "unique": 376,
      "ops": 107.734,
      "reps": 64,
      "cat": 0.1528,
      "raf": 903.283,
      "cyc": 14,
      "rate": 4849.0,
      "edges": 2726
    },
    {
      "epoch": 129000000,
      "H": 1.385,
      "unique": 343,
      "ops": 109.25,
      "reps": 55,
      "cat": 0.1352,
      "raf": 799.211,
      "cyc": 3,
      "rate": 4819.0,
      "edges": 2765
    },
    {
      "epoch": 130000000,
      "H": 1.438,
      "unique": 370,
      "ops": 108.767,
      "reps": 59,
      "cat": 0.1408,
      "raf": 832.41,
      "cyc": 2,
      "rate": 4758.0,
      "edges": 2811
    },
    {
      "epoch": 131000000,
      "H": 2.261,
      "unique": 546,
      "ops": 103.689,
      "reps": 114,
      "cat": 0.1996,
      "raf": 1179.583,
      "cyc": 6,
      "rate": 4732.0,
      "edges": 2785
    },
    {
      "epoch": 132000000,
      "H": 2.263,
      "unique": 546,
      "ops": 102.685,
      "reps": 99,
      "cat": 0.2108,
      "raf": 1245.994,
      "cyc": 3,
      "rate": 4712.0,
      "edges": 2660
    },
    {
      "epoch": 133000000,
      "H": 2.391,
      "unique": 558,
      "ops": 101.731,
      "reps": 118,
      "cat": 0.2218,
      "raf": 1311.181,
      "cyc": 5,
      "rate": 4689.0,
      "edges": 2626
    },
    {
      "epoch": 134000000,
      "H": 2.09,
      "unique": 485,
      "ops": 103.384,
      "reps": 99,
      "cat": 0.2028,
      "raf": 1198.686,
      "cyc": 9,
      "rate": 4673.0,
      "edges": 2634
    },
    {
      "epoch": 135000000,
      "H": 1.88,
      "unique": 461,
      "ops": 105.313,
      "reps": 93,
      "cat": 0.1809,
      "raf": 1069.038,
      "cyc": 9,
      "rate": 4664.0,
      "edges": 2671
    },
    {
      "epoch": 136000000,
      "H": 1.819,
      "unique": 460,
      "ops": 105.381,
      "reps": 72,
      "cat": 0.1798,
      "raf": 1062.826,
      "cyc": 3,
      "rate": 4653.0,
      "edges": 2722
    },
    {
      "epoch": 137000000,
      "H": 2.027,
      "unique": 504,
      "ops": 105.095,
      "reps": 86,
      "cat": 0.1829,
      "raf": 1081.119,
      "cyc": 3,
      "rate": 4643.0,
      "edges": 2752
    },
    {
      "epoch": 138000000,
      "H": 2.163,
      "unique": 515,
      "ops": 103.477,
      "reps": 102,
      "cat": 0.2017,
      "raf": 1192.149,
      "cyc": 11,
      "rate": 4630.0,
      "edges": 2751
    },
    {
      "epoch": 139000000,
      "H": 2.027,
      "unique": 500,
      "ops": 103.632,
      "reps": 98,
      "cat": 0.2,
      "raf": 1181.935,
      "cyc": 2,
      "rate": 4618.0,
      "edges": 2768
    },
    {
      "epoch": 140000000,
      "H": 2.033,
      "unique": 494,
      "ops": 104.194,
      "reps": 90,
      "cat": 0.1937,
      "raf": 1144.788,
      "cyc": 11,
      "rate": 4628.0,
      "edges": 2782
    },
    {
      "epoch": 141000000,
      "H": 2.427,
      "unique": 601,
      "ops": 101.902,
      "reps": 113,
      "cat": 0.2199,
      "raf": 1299.561,
      "cyc": 7,
      "rate": 4644.0,
      "edges": 2772
    },
    {
      "epoch": 142000000,
      "H": 2.369,
      "unique": 560,
      "ops": 101.114,
      "reps": 111,
      "cat": 0.2289,
      "raf": 1352.661,
      "cyc": 12,
      "rate": 4661.0,
      "edges": 2761
    },
    {
      "epoch": 143000000,
      "H": 2.148,
      "unique": 520,
      "ops": 102.407,
      "reps": 102,
      "cat": 0.214,
      "raf": 1265.073,
      "cyc": 4,
      "rate": 4677.0,
      "edges": 2776
    },
    {
      "epoch": 144000000,
      "H": 1.981,
      "unique": 476,
      "ops": 104.144,
      "reps": 95,
      "cat": 0.194,
      "raf": 1146.756,
      "cyc": 7,
      "rate": 4693.0,
      "edges": 2818
    },
    {
      "epoch": 145000000,
      "H": 2.357,
      "unique": 552,
      "ops": 102.253,
      "reps": 119,
      "cat": 0.2159,
      "raf": 1276.232,
      "cyc": 9,
      "rate": 4709.0,
      "edges": 2805
    },
    {
      "epoch": 146000000,
      "H": 2.251,
      "unique": 538,
      "ops": 101.935,
      "reps": 110,
      "cat": 0.2195,
      "raf": 1297.457,
      "cyc": 4,
      "rate": 4725.0,
      "edges": 2821
    },
    {
      "epoch": 147000000,
      "H": 2.224,
      "unique": 534,
      "ops": 102.297,
      "reps": 101,
      "cat": 0.2155,
      "raf": 1273.507,
      "cyc": 9,
      "rate": 4741.0,
      "edges": 2836
    },
    {
      "epoch": 148000000,
      "H": 2.399,
      "unique": 592,
      "ops": 101.821,
      "reps": 112,
      "cat": 0.221,
      "raf": 1305.968,
      "cyc": 2,
      "rate": 4756.0,
      "edges": 2734
    },
    {
      "epoch": 149000000,
      "H": 2.777,
      "unique": 661,
      "ops": 99.356,
      "reps": 135,
      "cat": 0.2496,
      "raf": 1475.506,
      "cyc": 11,
      "rate": 4772.0,
      "edges": 2678
    },
    {
      "epoch": 150000000,
      "H": 2.465,
      "unique": 590,
      "ops": 99.508,
      "reps": 104,
      "cat": 0.2473,
      "raf": 1461.628,
      "cyc": 10,
      "rate": 4788.0,
      "edges": 2669
    },
    {
      "epoch": 151000000,
      "H": 1.999,
      "unique": 477,
      "ops": 103.018,
      "reps": 98,
      "cat": 0.2069,
      "raf": 1222.931,
      "cyc": 4,
      "rate": 4803.0,
      "edges": 2717
    },
    {
      "epoch": 152000000,
      "H": 2.033,
      "unique": 480,
      "ops": 104.364,
      "reps": 94,
      "cat": 0.1914,
      "raf": 1131.359,
      "cyc": 29,
      "rate": 4818.0,
      "edges": 2733
    },
    {
      "epoch": 153000000,
      "H": 2.165,
      "unique": 527,
      "ops": 102.453,
      "reps": 94,
      "cat": 0.2135,
      "raf": 1261.976,
      "cyc": 2,
      "rate": 4833.0,
      "edges": 2744
    },
    {
      "epoch": 154000000,
      "H": 2.031,
      "unique": 497,
      "ops": 103.527,
      "reps": 94,
      "cat": 0.2015,
      "raf": 1190.73,
      "cyc": 5,
      "rate": 4847.0,
      "edges": 2747
    },
    {
      "epoch": 155000000,
      "H": 2.231,
      "unique": 552,
      "ops": 102.946,
      "reps": 102,
      "cat": 0.208,
      "raf": 1229.397,
      "cyc": 6,
      "rate": 4862.0,
      "edges": 2746
    },
    {
      "epoch": 156000000,
      "H": 2.151,
      "unique": 522,
      "ops": 102.979,
      "reps": 102,
      "cat": 0.2076,
      "raf": 1226.903,
      "cyc": 5,
      "rate": 4877.0,
      "edges": 2751
    },
    {
      "epoch": 157000000,
      "H": 2.182,
      "unique": 530,
      "ops": 102.9,
      "reps": 112,
      "cat": 0.2083,
      "raf": 1231.33,
      "cyc": 11,
      "rate": 4892.0,
      "edges": 2755
    },
    {
      "epoch": 158000000,
      "H": 2.355,
      "unique": 581,
      "ops": 102.293,
      "reps": 108,
      "cat": 0.2155,
      "raf": 1273.56,
      "cyc": 3,
      "rate": 4907.0,
      "edges": 2758
    },
    {
      "epoch": 159000000,
      "H": 2.335,
      "unique": 555,
      "ops": 102.166,
      "reps": 110,
      "cat": 0.2169,
      "raf": 1281.741,
      "cyc": 17,
      "rate": 4921.0,
      "edges": 2742
    },
    {
      "epoch": 160000000,
      "H": 2.154,
      "unique": 518,
      "ops": 102.542,
      "reps": 110,
      "cat": 0.2124,
      "raf": 1255.397,
      "cyc": 9,
      "rate": 4936.0,
      "edges": 2764
    },
    {
      "epoch": 161000000,
      "H": 2.309,
      "unique": 562,
      "ops": 101.388,
      "reps": 106,
      "cat": 0.2256,
      "raf": 1333.393,
      "cyc": 10,
      "rate": 4950.0,
      "edges": 2757
    },
    {
      "epoch": 162000000,
      "H": 2.249,
      "unique": 536,
      "ops": 102.184,
      "reps": 115,
      "cat": 0.2164,
      "raf": 1279.081,
      "cyc": 17,
      "rate": 4965.0,
      "edges": 2744
    },
    {
      "epoch": 163000000,
      "H": 1.888,
      "unique": 468,
      "ops": 104.4,
      "reps": 84,
      "cat": 0.1908,
      "raf": 1127.623,
      "cyc": 5,
      "rate": 4979.0,
      "edges": 2745
    },
    {
      "epoch": 164000000,
      "H": 1.741,
      "unique": 443,
      "ops": 106.362,
      "reps": 74,
      "cat": 0.1684,
      "raf": 995.21,
      "cyc": 7,
      "rate": 4992.0,
      "edges": 2751
    },
    {
      "epoch": 165000000,
      "H": 1.705,
      "unique": 454,
      "ops": 106.894,
      "reps": 63,
      "cat": 0.162,
      "raf": 957.761,
      "cyc": 4,
      "rate": 5005.0,
      "edges": 2760
    },
    {
      "epoch": 166000000,
      "H": 1.772,
      "unique": 437,
      "ops": 106.584,
      "reps": 67,
      "cat": 0.166,
      "raf": 981.261,
      "cyc": 3,
      "rate": 5019.0,
      "edges": 2787
    },
    {
      "epoch": 167000000,
      "H": 2.052,
      "unique": 500,
      "ops": 104.378,
      "reps": 95,
      "cat": 0.1917,
      "raf": 1133.085,
      "cyc": 12,
      "rate": 5032.0,
      "edges": 2750
    },
    {
      "epoch": 168000000,
      "H": 1.822,
      "unique": 438,
      "ops": 105.953,
      "reps": 84,
      "cat": 0.1733,
      "raf": 1024.183,
      "cyc": 3,
      "rate": 5045.0,
      "edges": 2749
    },
    {
      "epoch": 169000000,
      "H": 1.626,
      "unique": 397,
      "ops": 106.521,
      "reps": 70,
      "cat": 0.1665,
      "raf": 984.334,
      "cyc": 7,
      "rate": 5058.0,
      "edges": 2775
    },
    {
      "epoch": 170000000,
      "H": 1.587,
      "unique": 419,
      "ops": 108.302,
      "reps": 58,
      "cat": 0.1463,
      "raf": 864.883,
      "cyc": 2,
      "rate": 5071.0,
      "edges": 2791
    },
    {
      "epoch": 171000000,
      "H": 1.899,
      "unique": 465,
      "ops": 106.003,
      "reps": 93,
      "cat": 0.1727,
      "raf": 1020.992,
      "cyc": 10,
      "rate": 5083.0,
      "edges": 2793
    },
    {
      "epoch": 172000000,
      "H": 2.277,
      "unique": 557,
      "ops": 103.108,
      "reps": 105,
      "cat": 0.2059,
      "raf": 1216.843,
      "cyc": 7,
      "rate": 5097.0,
      "edges": 2779
    }
  ],
  "mega_charges": [
    {
      "epoch": 152000000,
      "cyc": 29,
      "raf": 1131.359
    }
  ],
  "sample_tapes": [
    "SSSSSSSS",
    "SSSSSSSS",
    "SSSSSSSS",
    "SSSSSSSS",
    "SSSSSSSS",
    "SSSSSSSS",
    "SSSSSSSS",
    "SSSSSSSS",
    "KISKKISS",
    "ISIISKKS",
    "SIKSSSSS",
    "IIKSISSI",
    "SKISSSSS",
    "SKSSSIII",
    "ISISSIIS",
    "SSSISSSI",
    "ISSSSIII",
    "ISSSSISI",
    "SSSISIKS",
    "KIIKSKKS",
    "SSISKISS",
    "IISSISSK",
    "SSSSSSIS",
    "SSSSSISI",
    "SISSIISI",
    "ISSSSSIS",
    "SSSSKSSI",
    "SSSSSSIK",
    "KIISIISI",
    "SSIIISSI"
  ],
  "tape_distribution": [
    {
      "t": "SSSSSSSS",
      "n": 3359
    },
    {
      "t": "IIIIIIII",
      "n": 19
    },
    {
      "t": "SSSSSSIS",
      "n": 9
    },
    {
      "t": "SSISSISI",
      "n": 7
    },
    {
      "t": "ISISSSIS",
      "n": 7
    },
    {
      "t": "SSSSSISI",
      "n": 6
    },
    {
      "t": "ISSSSSIS",
      "n": 6
    },
    {
      "t": "SSSISSSS",
      "n": 6
    },
    {
      "t": "SSSSSSSI",
      "n": 5
    },
    {
      "t": "SSSSSSSK",
      "n": 5
    },
    {
      "t": "SISISISI",
      "n": 5
    },
    {
      "t": "SSISSSIS",
      "n": 4
    },
    {
      "t": "SISSSSII",
      "n": 4
    },
    {
      "t": "ISSSISSS",
      "n": 4
    },
    {
      "t": "SSSSISSS",
      "n": 4
    },
    {
      "t": "SSSSISSI",
      "n": 3
    },
    {
      "t": "ISSISSSS",
      "n": 3
    },
    {
      "t": "SISSSISS",
      "n": 3
    },
    {
      "t": "SSSSSSKI",
      "n": 3
    },
    {
      "t": "SSISISII",
      "n": 3
    },
    {
      "t": "SSIKSISS",
      "n": 3
    },
    {
      "t": "SSSSIIIK",
      "n": 3
    },
    {
      "t": "SIIIIIII",
      "n": 3
    },
    {
      "t": "SSSSIIIS",
      "n": 3
    },
    {
      "t": "IISSSSSI",
      "n": 3
    },
    {
      "t": "SISSSIIS",
      "n": 3
    },
    {
      "t": "ISSSSISS",
      "n": 3
    },
    {
      "t": "ISSSSSSS",
      "n": 3
    },
    {
      "t": "SSSSSIII",
      "n": 3
    },
    {
      "t": "SSSSISII",
      "n": 2
    },
    {
      "t": "IIIIIISI",
      "n": 2
    },
    {
      "t": "SSIISSSK",
      "n": 2
    },
    {
      "t": "SIIISISI",
      "n": 2
    },
    {
      "t": "KSIISKSI",
      "n": 2
    },
    {
      "t": "ISSIIIII",
      "n": 2
    },
    {
      "t": "IIIISISI",
      "n": 2
    },
    {
      "t": "SSSISIIS",
      "n": 2
    },
    {
      "t": "SSSISIKI",
      "n": 2
    },
    {
      "t": "IISSIISI",
      "n": 2
    },
    {
      "t": "SISIKIIS",
      "n": 2
    },
    {
      "t": "SIIISIII",
      "n": 2
    },
    {
      "t": "SKSKSKIS",
      "n": 2
    },
    {
      "t": "IISSSSII",
      "n": 2
    },
    {
      "t": "KSSISSSI",
      "n": 2
    },
    {
      "t": "ISISIIII",
      "n": 2
    },
    {
      "t": "SSISSSSS",
      "n": 2
    },
    {
      "t": "SSSSSISS",
      "n": 2
    },
    {
      "t": "KSSSSISS",
      "n": 2
    },
    {
      "t": "KISSSKSI",
      "n": 2
    },
    {
      "t": "SSSSSKSS",
      "n": 2
    },
    {
      "t": "SISIISSI",
      "n": 2
    },
    {
      "t": "ISSISISS",
      "n": 2
    },
    {
      "t": "SSKIIISS",
      "n": 2
    },
    {
      "t": "SSSIIKSI",
      "n": 2
    },
    {
      "t": "SISSISSS",
      "n": 2
    },
    {
      "t": "SSSSKSSS",
      "n": 2
    },
    {
      "t": "IISISIKI",
      "n": 2
    },
    {
      "t": "SSISIKII",
      "n": 2
    },
    {
      "t": "SIKIKSII",
      "n": 2
    },
    {
      "t": "SIISIISK",
      "n": 2
    },
    {
      "t": "ISSSISSI",
      "n": 2
    },
    {
      "t": "IISSSISS",
      "n": 2
    },
    {
      "t": "SISISSII",
      "n": 2
    },
    {
      "t": "IISISISI",
      "n": 2
    },
    {
      "t": "IISISSSS",
      "n": 2
    },
    {
      "t": "SSISISSI",
      "n": 2
    },
    {
      "t": "SISIIISI",
      "n": 2
    },
    {
      "t": "KSSSSSSS",
      "n": 2
    },
    {
      "t": "ISISSSSS",
      "n": 2
    },
    {
      "t": "SSSKIIII",
      "n": 2
    },
    {
      "t": "IISISSSI",
      "n": 2
    },
    {
      "t": "SSSSIISK",
      "n": 2
    },
    {
      "t": "SSISSIIS",
      "n": 2
    },
    {
      "t": "SSSISSIS",
      "n": 2
    },
    {
      "t": "ISISISIS",
      "n": 2
    },
    {
      "t": "IISSISSK",
      "n": 2
    },
    {
      "t": "SSIIISIS",
      "n": 2
    },
    {
      "t": "SSSSSIIK",
      "n": 2
    },
    {
      "t": "IISSISSS",
      "n": 2
    },
    {
      "t": "IISISSIS",
      "n": 2
    },
    {
      "t": "KSISIISS",
      "n": 2
    },
    {
      "t": "IISSKSSI",
      "n": 2
    },
    {
      "t": "IIISISSS",
      "n": 2
    },
    {
      "t": "KSSKIIII",
      "n": 2
    },
    {
      "t": "IISIIIIS",
      "n": 2
    },
    {
      "t": "SSSSSSIK",
      "n": 2
    },
    {
      "t": "SSSIISIS",
      "n": 2
    },
    {
      "t": "KIIISSSI",
      "n": 2
    },
    {
      "t": "SSSISSKI",
      "n": 2
    },
    {
      "t": "IISIIIKS",
      "n": 2
    },
    {
      "t": "SSISIIII",
      "n": 2
    },
    {
      "t": "SSSSIKKI",
      "n": 2
    },
    {
      "t": "SIISIIKS",
      "n": 2
    },
    {
      "t": "SSSISSSI",
      "n": 2
    },
    {
      "t": "ISSISSKS",
      "n": 2
    },
    {
      "t": "IIISIKII",
      "n": 2
    },
    {
      "t": "IIIISIII",
      "n": 2
    },
    {
      "t": "SKISISSS",
      "n": 2
    },
    {
      "t": "SISISSSI",
      "n": 2
    },
    {
      "t": "SSIIIIKI",
      "n": 2
    },
    {
      "t": "SSSIISSI",
      "n": 2
    },
    {
      "t": "ISSSSIII",
      "n": 2
    },
    {
      "t": "KSSSISSS",
      "n": 2
    },
    {
      "t": "SSIISIII",
      "n": 2
    },
    {
      "t": "SSSSSSKS",
      "n": 2
    },
    {
      "t": "ISISIISI",
      "n": 1
    },
    {
      "t": "KSSSSISI",
      "n": 1
    },
    {
      "t": "SISISKKS",
      "n": 1
    },
    {
      "t": "KIIKSSIK",
      "n": 1
    },
    {
      "t": "SIISKIII",
      "n": 1
    },
    {
      "t": "SKSSSISK",
      "n": 1
    },
    {
      "t": "SIISIKII",
      "n": 1
    },
    {
      "t": "SKKIISIS",
      "n": 1
    },
    {
      "t": "SSISSSSK",
      "n": 1
    },
    {
      "t": "KKISSSSS",
      "n": 1
    },
    {
      "t": "KKSIIIIS",
      "n": 1
    },
    {
      "t": "SSIKSISI",
      "n": 1
    },
    {
      "t": "SKKSSKII",
      "n": 1
    },
    {
      "t": "KISSKIII",
      "n": 1
    },
    {
      "t": "SKSKIISI",
      "n": 1
    },
    {
      "t": "IKKKIIIK",
      "n": 1
    },
    {
      "t": "ISIIKKKI",
      "n": 1
    },
    {
      "t": "SIKISSSS",
      "n": 1
    },
    {
      "t": "SSIISSKK",
      "n": 1
    },
    {
      "t": "SSKIISSI",
      "n": 1
    },
    {
      "t": "ISSSSSKS",
      "n": 1
    },
    {
      "t": "SSKKSKII",
      "n": 1
    },
    {
      "t": "SIIIIKSI",
      "n": 1
    },
    {
      "t": "SIKSSIIS",
      "n": 1
    },
    {
      "t": "SSSIIKKI",
      "n": 1
    },
    {
      "t": "ISIISISS",
      "n": 1
    },
    {
      "t": "KIIISIIS",
      "n": 1
    },
    {
      "t": "KKIISISI",
      "n": 1
    },
    {
      "t": "SISSIIIS",
      "n": 1
    },
    {
      "t": "SISIISKI",
      "n": 1
    },
    {
      "t": "SSSISIII",
      "n": 1
    },
    {
      "t": "SKSSKSII",
      "n": 1
    },
    {
      "t": "SSKIIISI",
      "n": 1
    },
    {
      "t": "IKSSIISI",
      "n": 1
    },
    {
      "t": "SKISSIKI",
      "n": 1
    },
    {
      "t": "SSKISKKI",
      "n": 1
    },
    {
      "t": "SSSSSSII",
      "n": 1
    },
    {
      "t": "SISSIISI",
      "n": 1
    },
    {
      "t": "SIIKSIKI",
      "n": 1
    },
    {
      "t": "KIIKISIK",
      "n": 1
    },
    {
      "t": "SISKSSII",
      "n": 1
    },
    {
      "t": "SIIIISII",
      "n": 1
    },
    {
      "t": "ISIIKSSS",
      "n": 1
    },
    {
      "t": "SKISSSIS",
      "n": 1
    },
    {
      "t": "SSIIISKI",
      "n": 1
    },
    {
      "t": "ISIKSISS",
      "n": 1
    },
    {
      "t": "KKSKIIII",
      "n": 1
    },
    {
      "t": "KSIKSSII",
      "n": 1
    },
    {
      "t": "SSSIISKI",
      "n": 1
    },
    {
      "t": "SSISSSKK",
      "n": 1
    },
    {
      "t": "KISSSSKI",
      "n": 1
    },
    {
      "t": "SKSISSSI",
      "n": 1
    },
    {
      "t": "SSKSSKIK",
      "n": 1
    },
    {
      "t": "KKIISISS",
      "n": 1
    },
    {
      "t": "SIKIISSI",
      "n": 1
    },
    {
      "t": "KISIIISS",
      "n": 1
    },
    {
      "t": "SSKIISII",
      "n": 1
    },
    {
      "t": "ISIIKSSI",
      "n": 1
    },
    {
      "t": "KSSISISS",
      "n": 1
    },
    {
      "t": "ISIISKKS",
      "n": 1
    },
    {
      "t": "SSKKSIII",
      "n": 1
    },
    {
      "t": "IIIKSIIS",
      "n": 1
    },
    {
      "t": "ISSSIIIK",
      "n": 1
    },
    {
      "t": "KKISISIS",
      "n": 1
    },
    {
      "t": "SSKIIKSK",
      "n": 1
    },
    {
      "t": "IKSSSIII",
      "n": 1
    },
    {
      "t": "SSSSIKII",
      "n": 1
    },
    {
      "t": "SIIKSSSI",
      "n": 1
    },
    {
      "t": "KISSSSIS",
      "n": 1
    },
    {
      "t": "KISSKISI",
      "n": 1
    },
    {
      "t": "SKSISISI",
      "n": 1
    },
    {
      "t": "SSSSISKK",
      "n": 1
    },
    {
      "t": "SSIKIKIS",
      "n": 1
    },
    {
      "t": "SISSIISS",
      "n": 1
    },
    {
      "t": "KIKSISIS",
      "n": 1
    },
    {
      "t": "KKKKKIII",
      "n": 1
    },
    {
      "t": "SSISKSSS",
      "n": 1
    },
    {
      "t": "SIIIISIK",
      "n": 1
    },
    {
      "t": "IISSIIKS",
      "n": 1
    },
    {
      "t": "SISIKKIS",
      "n": 1
    },
    {
      "t": "KSKISSSS",
      "n": 1
    },
    {
      "t": "IKIISISI",
      "n": 1
    },
    {
      "t": "SISSSSKI",
      "n": 1
    },
    {
      "t": "SIKIIISK",
      "n": 1
    },
    {
      "t": "IKSKSIKI",
      "n": 1
    },
    {
      "t": "SKSKSSIS",
      "n": 1
    },
    {
      "t": "IKISIISI",
      "n": 1
    },
    {
      "t": "SSSSIIKI",
      "n": 1
    },
    {
      "t": "KKKSKKII",
      "n": 1
    },
    {
      "t": "IIKIISII",
      "n": 1
    },
    {
      "t": "ISKSSSIK",
      "n": 1
    },
    {
      "t": "ISKISSSI",
      "n": 1
    },
    {
      "t": "SIKISKSI",
      "n": 1
    },
    {
      "t": "SIIIISSS",
      "n": 1
    },
    {
      "t": "SSKSSIII",
      "n": 1
    },
    {
      "t": "ISSIKSII",
      "n": 1
    },
    {
      "t": "SISIKSSS",
      "n": 1
    },
    {
      "t": "SIIKSSKI",
      "n": 1
    },
    {
      "t": "SISISIII",
      "n": 1
    },
    {
      "t": "ISIIISIS",
      "n": 1
    },
    {
      "t": "SKISIKSI",
      "n": 1
    },
    {
      "t": "KSIISSII",
      "n": 1
    },
    {
      "t": "SSSISSKK",
      "n": 1
    },
    {
      "t": "KSKIKIKI",
      "n": 1
    },
    {
      "t": "ISSIIIIS",
      "n": 1
    },
    {
      "t": "KSSIISII",
      "n": 1
    },
    {
      "t": "IKSKISSS",
      "n": 1
    },
    {
      "t": "SKKIIISI",
      "n": 1
    },
    {
      "t": "SKKSIIII",
      "n": 1
    },
    {
      "t": "IIIKSIII",
      "n": 1
    },
    {
      "t": "IKIISSKI",
      "n": 1
    },
    {
      "t": "IIISSSII",
      "n": 1
    },
    {
      "t": "IISIKISI",
      "n": 1
    },
    {
      "t": "SSKISSSI",
      "n": 1
    },
    {
      "t": "SISIKISI",
      "n": 1
    },
    {
      "t": "SSIIISIK",
      "n": 1
    },
    {
      "t": "SIISKSIS",
      "n": 1
    },
    {
      "t": "SSKSIKII",
      "n": 1
    },
    {
      "t": "ISISSSKS",
      "n": 1
    },
    {
      "t": "KIIIKIIS",
      "n": 1
    },
    {
      "t": "SKSIKIII",
      "n": 1
    },
    {
      "t": "SSKSKISS",
      "n": 1
    },
    {
      "t": "SSKISSIS",
      "n": 1
    },
    {
      "t": "SIIKKSSK",
      "n": 1
    },
    {
      "t": "IISIISKS",
      "n": 1
    },
    {
      "t": "SISISIIS",
      "n": 1
    },
    {
      "t": "SSSIIISI",
      "n": 1
    },
    {
      "t": "IKSSIKII",
      "n": 1
    },
    {
      "t": "ISKSKISI",
      "n": 1
    },
    {
      "t": "IIKISSIK",
      "n": 1
    },
    {
      "t": "SIIISSII",
      "n": 1
    },
    {
      "t": "KIKSSIII",
      "n": 1
    },
    {
      "t": "SSSIIKSK",
      "n": 1
    },
    {
      "t": "SKSSKSKK",
      "n": 1
    },
    {
      "t": "KIIISSII",
      "n": 1
    },
    {
      "t": "SKKSKKII",
      "n": 1
    },
    {
      "t": "KSIISSSI",
      "n": 1
    },
    {
      "t": "IIKSISSI",
      "n": 1
    },
    {
      "t": "SIKIKISI",
      "n": 1
    },
    {
      "t": "SKSIIIIK",
      "n": 1
    },
    {
      "t": "SKSISSII",
      "n": 1
    },
    {
      "t": "ISSKIKSS",
      "n": 1
    },
    {
      "t": "ISKSSIII",
      "n": 1
    },
    {
      "t": "KISISISS",
      "n": 1
    },
    {
      "t": "SSSKSIII",
      "n": 1
    },
    {
      "t": "KISSKSII",
      "n": 1
    },
    {
      "t": "SISSKISS",
      "n": 1
    },
    {
      "t": "ISSSSSII",
      "n": 1
    },
    {
      "t": "SSSKSISI",
      "n": 1
    },
    {
      "t": "SIKKISSS",
      "n": 1
    },
    {
      "t": "ISISSISI",
      "n": 1
    },
    {
      "t": "SSKIKIIS",
      "n": 1
    },
    {
      "t": "ISISISSI",
      "n": 1
    },
    {
      "t": "SKSKIIII",
      "n": 1
    },
    {
      "t": "IIKKIISI",
      "n": 1
    },
    {
      "t": "SIISISSS",
      "n": 1
    },
    {
      "t": "IIIISSSK",
      "n": 1
    },
    {
      "t": "IIIKSKIS",
      "n": 1
    },
    {
      "t": "KISKKISS",
      "n": 1
    },
    {
      "t": "SKSISKSI",
      "n": 1
    },
    {
      "t": "IIKKISIS",
      "n": 1
    },
    {
      "t": "SSSSISKI",
      "n": 1
    },
    {
      "t": "IISSIKSI",
      "n": 1
    },
    {
      "t": "SKKIKISK",
      "n": 1
    },
    {
      "t": "KIIIKSSI",
      "n": 1
    },
    {
      "t": "KKISIIKI",
      "n": 1
    },
    {
      "t": "SSSISIKS",
      "n": 1
    },
    {
      "t": "KIISISSS",
      "n": 1
    },
    {
      "t": "KSISISSS",
      "n": 1
    },
    {
      "t": "SSSISKSS",
      "n": 1
    },
    {
      "t": "SKSIISIK",
      "n": 1
    },
    {
      "t": "SKSSSSSS",
      "n": 1
    },
    {
      "t": "KKKSSSIK",
      "n": 1
    },
    {
      "t": "SIIIKSSS",
      "n": 1
    },
    {
      "t": "SIKSISII",
      "n": 1
    },
    {
      "t": "KISSKISS",
      "n": 1
    },
    {
      "t": "SISIIIIK",
      "n": 1
    },
    {
      "t": "SIIISISS",
      "n": 1
    },
    {
      "t": "SIISISII",
      "n": 1
    },
    {
      "t": "IKISSISS",
      "n": 1
    },
    {
      "t": "ISKISSII",
      "n": 1
    },
    {
      "t": "SIKIIIIS",
      "n": 1
    },
    {
      "t": "SIKSSSSS",
      "n": 1
    },
    {
      "t": "SSIISSSS",
      "n": 1
    },
    {
      "t": "SSIIIIIS",
      "n": 1
    },
    {
      "t": "KSIIIIKS",
      "n": 1
    },
    {
      "t": "SIIIIIIK",
      "n": 1
    },
    {
      "t": "SSISKSSI",
      "n": 1
    },
    {
      "t": "IISIIISI",
      "n": 1
    },
    {
      "t": "SSSISSII",
      "n": 1
    },
    {
      "t": "SISSIIII",
      "n": 1
    },
    {
      "t": "SISSSSIK",
      "n": 1
    },
    {
      "t": "SSIIKSSS",
      "n": 1
    },
    {
      "t": "ISSIKIII",
      "n": 1
    },
    {
      "t": "KKIIIKSS",
      "n": 1
    },
    {
      "t": "KISSSSSS",
      "n": 1
    },
    {
      "t": "SIISIIII",
      "n": 1
    },
    {
      "t": "IKSSIIII",
      "n": 1
    },
    {
      "t": "SKSKSIII",
      "n": 1
    },
    {
      "t": "SISSSKIS",
      "n": 1
    },
    {
      "t": "KKISSIIK",
      "n": 1
    },
    {
      "t": "SSSSIIII",
      "n": 1
    },
    {
      "t": "KSSISSSK",
      "n": 1
    },
    {
      "t": "ISSSIIIS",
      "n": 1
    },
    {
      "t": "SIIKIIKS",
      "n": 1
    },
    {
      "t": "SSSKSSIS",
      "n": 1
    },
    {
      "t": "SSISSKSK",
      "n": 1
    },
    {
      "t": "ISISSIIS",
      "n": 1
    },
    {
      "t": "SISIIKSS",
      "n": 1
    },
    {
      "t": "ISISSISS",
      "n": 1
    },
    {
      "t": "IKIKIISS",
      "n": 1
    },
    {
      "t": "KISSSSSI",
      "n": 1
    },
    {
      "t": "ISISSSII",
      "n": 1
    },
    {
      "t": "SIIKSKSI",
      "n": 1
    },
    {
      "t": "IKIISIIK",
      "n": 1
    },
    {
      "t": "SKSIISII",
      "n": 1
    },
    {
      "t": "SKKSSSII",
      "n": 1
    },
    {
      "t": "KSKIIIKS",
      "n": 1
    },
    {
      "t": "SKIIISSI",
      "n": 1
    },
    {
      "t": "KSSIISSI",
      "n": 1
    },
    {
      "t": "ISSSIIII",
      "n": 1
    },
    {
      "t": "SSSSSIKI",
      "n": 1
    },
    {
      "t": "IISIKKKS",
      "n": 1
    },
    {
      "t": "SSSIIKIS",
      "n": 1
    },
    {
      "t": "SKSIIISI",
      "n": 1
    },
    {
      "t": "KIISIISI",
      "n": 1
    },
    {
      "t": "ISSSSISI",
      "n": 1
    },
    {
      "t": "SKKKISSI",
      "n": 1
    },
    {
      "t": "ISIIISKK",
      "n": 1
    },
    {
      "t": "KIISSISI",
      "n": 1
    },
    {
      "t": "SKSSKISI",
      "n": 1
    },
    {
      "t": "SKSKSISS",
      "n": 1
    },
    {
      "t": "KKSIISII",
      "n": 1
    },
    {
      "t": "SIKKSSII",
      "n": 1
    },
    {
      "t": "SSIIIKSS",
      "n": 1
    },
    {
      "t": "SISSISSI",
      "n": 1
    },
    {
      "t": "SKISSSSI",
      "n": 1
    },
    {
      "t": "IKSSSSII",
      "n": 1
    },
    {
      "t": "SSSSKIII",
      "n": 1
    },
    {
      "t": "SISSSIKK",
      "n": 1
    },
    {
      "t": "ISISSSSI",
      "n": 1
    },
    {
      "t": "KKIISSSS",
      "n": 1
    },
    {
      "t": "SKSIIISS",
      "n": 1
    },
    {
      "t": "SKSSSIII",
      "n": 1
    },
    {
      "t": "SSSKSSKS",
      "n": 1
    },
    {
      "t": "SISIKIII",
      "n": 1
    },
    {
      "t": "SSSSSIKS",
      "n": 1
    },
    {
      "t": "ISISKSKI",
      "n": 1
    },
    {
      "t": "SIKKIISK",
      "n": 1
    },
    {
      "t": "SIKKIIII",
      "n": 1
    },
    {
      "t": "IIISKKIS",
      "n": 1
    },
    {
      "t": "SISSKIII",
      "n": 1
    },
    {
      "t": "SSISIISI",
      "n": 1
    },
    {
      "t": "IKIISSIS",
      "n": 1
    },
    {
      "t": "IISKISSI",
      "n": 1
    },
    {
      "t": "SISSIKII",
      "n": 1
    },
    {
      "t": "KSKIKIIS",
      "n": 1
    },
    {
      "t": "IIISISII",
      "n": 1
    },
    {
      "t": "SKKIKSII",
      "n": 1
    },
    {
      "t": "SKSKSKKS",
      "n": 1
    },
    {
      "t": "KKSSISKS",
      "n": 1
    },
    {
      "t": "SKSSISSS",
      "n": 1
    },
    {
      "t": "KSKKISKI",
      "n": 1
    },
    {
      "t": "SKIISIII",
      "n": 1
    },
    {
      "t": "SISSSSIS",
      "n": 1
    },
    {
      "t": "KSSIIKKS",
      "n": 1
    },
    {
      "t": "IKKKIISS",
      "n": 1
    },
    {
      "t": "IISKISII",
      "n": 1
    },
    {
      "t": "KISSSSIK",
      "n": 1
    },
    {
      "t": "SISSSSKS",
      "n": 1
    },
    {
      "t": "SIISIKSI",
      "n": 1
    },
    {
      "t": "SIISIISS",
      "n": 1
    },
    {
      "t": "ISSKIKKS",
      "n": 1
    },
    {
      "t": "IIIISIKK",
      "n": 1
    },
    {
      "t": "SKIIIIKI",
      "n": 1
    },
    {
      "t": "SISSISSK",
      "n": 1
    },
    {
      "t": "KSSIIISS",
      "n": 1
    },
    {
      "t": "KIIKSKKS",
      "n": 1
    },
    {
      "t": "SISKSKSI",
      "n": 1
    },
    {
      "t": "KSIKSSSI",
      "n": 1
    },
    {
      "t": "SSKSSSIS",
      "n": 1
    },
    {
      "t": "SIKIIKSI",
      "n": 1
    },
    {
      "t": "ISKSIKSS",
      "n": 1
    },
    {
      "t": "ISSIKISK",
      "n": 1
    },
    {
      "t": "ISSISSSI",
      "n": 1
    },
    {
      "t": "ISIISSSI",
      "n": 1
    },
    {
      "t": "ISIIIIII",
      "n": 1
    },
    {
      "t": "SSSSKISI",
      "n": 1
    },
    {
      "t": "IISKSSSS",
      "n": 1
    },
    {
      "t": "SSSKSSII",
      "n": 1
    },
    {
      "t": "SKSIKIKI",
      "n": 1
    },
    {
      "t": "SIIISSIK",
      "n": 1
    },
    {
      "t": "SIISIIKK",
      "n": 1
    },
    {
      "t": "SISISISS",
      "n": 1
    },
    {
      "t": "ISKIKSIK",
      "n": 1
    },
    {
      "t": "SSKKSSSI",
      "n": 1
    },
    {
      "t": "SISSSISI",
      "n": 1
    },
    {
      "t": "SSKKISSI",
      "n": 1
    },
    {
      "t": "KSSSISSI",
      "n": 1
    },
    {
      "t": "SISSSIIK",
      "n": 1
    },
    {
      "t": "ISIISSIK",
      "n": 1
    },
    {
      "t": "ISSSSSSI",
      "n": 1
    },
    {
      "t": "SISISSIS",
      "n": 1
    },
    {
      "t": "SIISIIIK",
      "n": 1
    },
    {
      "t": "IKKSIIII",
      "n": 1
    },
    {
      "t": "KIKISKSK",
      "n": 1
    },
    {
      "t": "KIISSISS",
      "n": 1
    },
    {
      "t": "SSKKISII",
      "n": 1
    },
    {
      "t": "SSISSIII",
      "n": 1
    },
    {
      "t": "KKISSIII",
      "n": 1
    },
    {
      "t": "IIIIIISS",
      "n": 1
    },
    {
      "t": "ISSIISIK",
      "n": 1
    },
    {
      "t": "SIISKIKS",
      "n": 1
    },
    {
      "t": "KIIKSKSS",
      "n": 1
    },
    {
      "t": "SKSKSKSK",
      "n": 1
    },
    {
      "t": "SKKSIISK",
      "n": 1
    },
    {
      "t": "KKISISKS",
      "n": 1
    },
    {
      "t": "SISIISIK",
      "n": 1
    },
    {
      "t": "SSIIIIII",
      "n": 1
    },
    {
      "t": "SIIISSSS",
      "n": 1
    },
    {
      "t": "SIIKSSSS",
      "n": 1
    },
    {
      "t": "IISSSIII",
      "n": 1
    },
    {
      "t": "SIIKSISS",
      "n": 1
    },
    {
      "t": "KSSSIISI",
      "n": 1
    },
    {
      "t": "IKSSISSI",
      "n": 1
    },
    {
      "t": "IIKSSSIS",
      "n": 1
    },
    {
      "t": "ISSSISKS",
      "n": 1
    },
    {
      "t": "SISSISKI",
      "n": 1
    },
    {
      "t": "SISSSSSS",
      "n": 1
    },
    {
      "t": "ISISSKIK",
      "n": 1
    },
    {
      "t": "KSIISIII",
      "n": 1
    },
    {
      "t": "SISISSSS",
      "n": 1
    },
    {
      "t": "ISIISIIS",
      "n": 1
    },
    {
      "t": "SKSISIIS",
      "n": 1
    },
    {
      "t": "KKSSSISK",
      "n": 1
    },
    {
      "t": "SIIKSSIS",
      "n": 1
    },
    {
      "t": "SIKISIIS",
      "n": 1
    },
    {
      "t": "KSKSISSS",
      "n": 1
    },
    {
      "t": "SKISISSI",
      "n": 1
    },
    {
      "t": "SSIIIKSI",
      "n": 1
    },
    {
      "t": "SSIISISI",
      "n": 1
    },
    {
      "t": "SSIIIISI",
      "n": 1
    },
    {
      "t": "SISIIISS",
      "n": 1
    },
    {
      "t": "ISIKIIII",
      "n": 1
    },
    {
      "t": "SSISIISS",
      "n": 1
    },
    {
      "t": "SKKIISSK",
      "n": 1
    },
    {
      "t": "SISSIKSS",
      "n": 1
    },
    {
      "t": "IKSISSSI",
      "n": 1
    },
    {
      "t": "SIIIIKKI",
      "n": 1
    },
    {
      "t": "SSSKSISK",
      "n": 1
    },
    {
      "t": "ISSSKIII",
      "n": 1
    },
    {
      "t": "KISSISII",
      "n": 1
    },
    {
      "t": "SSSIKKII",
      "n": 1
    },
    {
      "t": "IIIIIKSK",
      "n": 1
    },
    {
      "t": "IIIKSSSS",
      "n": 1
    },
    {
      "t": "SKISSSSS",
      "n": 1
    },
    {
      "t": "ISISKSSI",
      "n": 1
    },
    {
      "t": "ISIIKIIS",
      "n": 1
    },
    {
      "t": "SISIKSKI",
      "n": 1
    },
    {
      "t": "KIIKSSKS",
      "n": 1
    },
    {
      "t": "IIISKIKI",
      "n": 1
    },
    {
      "t": "KISKSSSI",
      "n": 1
    },
    {
      "t": "ISSIISII",
      "n": 1
    },
    {
      "t": "SIIISIIS",
      "n": 1
    },
    {
      "t": "IIISSISI",
      "n": 1
    },
    {
      "t": "SSIIIKIS",
      "n": 1
    },
    {
      "t": "SIIKSISI",
      "n": 1
    },
    {
      "t": "SKISSIIS",
      "n": 1
    },
    {
      "t": "SISIIIKS",
      "n": 1
    },
    {
      "t": "SKSISSSK",
      "n": 1
    },
    {
      "t": "SKSISSIK",
      "n": 1
    },
    {
      "t": "IKSKSSSI",
      "n": 1
    },
    {
      "t": "IKSISIIS",
      "n": 1
    },
    {
      "t": "SSIIISSI",
      "n": 1
    },
    {
      "t": "IISKKSII",
      "n": 1
    },
    {
      "t": "KKIISKIK",
      "n": 1
    },
    {
      "t": "KKISSISS",
      "n": 1
    },
    {
      "t": "IISSSSIS",
      "n": 1
    },
    {
      "t": "IIKSSISS",
      "n": 1
    },
    {
      "t": "IIIISIIS",
      "n": 1
    },
    {
      "t": "SIIIISSI",
      "n": 1
    },
    {
      "t": "IKIIIISI",
      "n": 1
    },
    {
      "t": "SKKKISIS",
      "n": 1
    },
    {
      "t": "ISISIIIS",
      "n": 1
    },
    {
      "t": "KSISIKII",
      "n": 1
    },
    {
      "t": "SISIISSK",
      "n": 1
    },
    {
      "t": "IISIIIII",
      "n": 1
    },
    {
      "t": "KKIISSSI",
      "n": 1
    },
    {
      "t": "KIKIISKS",
      "n": 1
    },
    {
      "t": "KIISSSSS",
      "n": 1
    },
    {
      "t": "SSIISSIS",
      "n": 1
    },
    {
      "t": "ISSISKSI",
      "n": 1
    },
    {
      "t": "ISIISSII",
      "n": 1
    },
    {
      "t": "IKIISKIS",
      "n": 1
    },
    {
      "t": "SSSSKISS",
      "n": 1
    },
    {
      "t": "SISSISIS",
      "n": 1
    },
    {
      "t": "SIISSSII",
      "n": 1
    },
    {
      "t": "SKKISSSS",
      "n": 1
    },
    {
      "t": "IIISIISS",
      "n": 1
    },
    {
      "t": "SISSIKSI",
      "n": 1
    },
    {
      "t": "SSSIISII",
      "n": 1
    },
    {
      "t": "SIKIIISS",
      "n": 1
    },
    {
      "t": "SIKKIIIK",
      "n": 1
    },
    {
      "t": "SSIISKII",
      "n": 1
    },
    {
      "t": "SIKSKIII",
      "n": 1
    },
    {
      "t": "ISISIKSS",
      "n": 1
    },
    {
      "t": "SISISIKK",
      "n": 1
    },
    {
      "t": "ISIKSKSI",
      "n": 1
    },
    {
      "t": "SSKISISS",
      "n": 1
    },
    {
      "t": "IIKSKIII",
      "n": 1
    },
    {
      "t": "SKIIIIII",
      "n": 1
    },
    {
      "t": "SIISSIIS",
      "n": 1
    },
    {
      "t": "SSSSIIKS",
      "n": 1
    },
    {
      "t": "SISSISII",
      "n": 1
    },
    {
      "t": "SSSISISI",
      "n": 1
    },
    {
      "t": "SSKIIKSI",
      "n": 1
    },
    {
      "t": "SSSIKSII",
      "n": 1
    },
    {
      "t": "KSSSKKSS",
      "n": 1
    },
    {
      "t": "IKSKKSIK",
      "n": 1
    },
    {
      "t": "SSSSIISS",
      "n": 1
    },
    {
      "t": "KIIKSSII",
      "n": 1
    },
    {
      "t": "SSSSSIIS",
      "n": 1
    },
    {
      "t": "IIKISSII",
      "n": 1
    },
    {
      "t": "SIKKSISS",
      "n": 1
    },
    {
      "t": "KKSISSIS",
      "n": 1
    },
    {
      "t": "SSISKKIK",
      "n": 1
    },
    {
      "t": "KISSIISS",
      "n": 1
    },
    {
      "t": "SSISKISS",
      "n": 1
    },
    {
      "t": "KSSSSKSS",
      "n": 1
    },
    {
      "t": "KIKSIISI",
      "n": 1
    },
    {
      "t": "KKSSIIII",
      "n": 1
    },
    {
      "t": "SSSISISS",
      "n": 1
    },
    {
      "t": "SSISIISK",
      "n": 1
    },
    {
      "t": "KSKISSSI",
      "n": 1
    },
    {
      "t": "SSSSIKSI",
      "n": 1
    },
    {
      "t": "IIIISSSI",
      "n": 1
    },
    {
      "t": "SKISKIII",
      "n": 1
    },
    {
      "t": "SSKISKSS",
      "n": 1
    },
    {
      "t": "SSIKIIII",
      "n": 1
    },
    {
      "t": "SSISISIS",
      "n": 1
    },
    {
      "t": "SSSSKSSI",
      "n": 1
    },
    {
      "t": "ISISSSSK",
      "n": 1
    },
    {
      "t": "SSKSSISI",
      "n": 1
    },
    {
      "t": "SIKSSSSK",
      "n": 1
    },
    {
      "t": "SKIKSISS",
      "n": 1
    },
    {
      "t": "IKIISIII",
      "n": 1
    },
    {
      "t": "KIKSKISS",
      "n": 1
    },
    {
      "t": "SSSSSKKK",
      "n": 1
    },
    {
      "t": "IISSISSI",
      "n": 1
    },
    {
      "t": "SIISSISI",
      "n": 1
    },
    {
      "t": "SSISKSKI",
      "n": 1
    },
    {
      "t": "SKSSKKSS",
      "n": 1
    }
  ],
  "run_label": "continuous_v1",
  "peak_rate": 6013
}